<?xml version="1.0"?>
<!DOCTYPE hibernate-mapping PUBLIC 
	"-//Hibernate/Hibernate Mapping DTD 3.0//EN"
	"http://hibernate.sourceforge.net/hibernate-mapping-3.0.dtd">
<hibernate-mapping package="zhishusz.housepresell.database.po">
	<class name="Tg_ProInspectionSchedule_View" table="Tg_ProInspectionSchedule_View" dynamic-update="true" dynamic-insert="true">
		<id name="tableId">
			<generator class="sequence">
				<param name="sequence">Seq_Tg_ProInspectionSchedule_View</param>
			</generator>
		</id>

		<property name="cityRegion">
			<column name="cityRegion">
				<comment>区域</comment>
			</column>
		</property>
		<property name="companyName">
			<column name="companyName">
				<comment>开发企业</comment>
			</column>
		</property>
		<property name="projectName">
			<column name="projectName">
				<comment>项目</comment>
			</column>
		</property>
		<property name="eCodeFromConstruction">
			<column name="eCodeFromConstruction">
				<comment>楼幢</comment>
			</column>
		</property>
		<property name="upTotalFloorNumber">
			<column name="upTotalFloorNumber">
				<comment>地上楼层数（总 ）</comment>
			</column>
		</property>
		<property name="currentLimitedNote">
			<column name="currentLimitedNote">
				<comment>当前受限节点</comment>
			</column>
		</property>
		<property name="currentBuildProgress">
			<column name="currentBuildProgress">
				<comment>当前建设进度</comment>
			</column>
		</property>
		<property name="progressOfUpdateTime">
			<column name="progressOfUpdateTime">
				<comment>进度更新时间</comment>
			</column>
		</property>
		<property name="nextChangeNode">
			<column name="nextChangeNode">
				<comment>下一变更节点</comment>
			</column>
		</property>
		<property name="forecastNextChangeTime">
			<column name="forecastNextChangeTime">
				<comment>预测变更时间</comment>
			</column>
		</property>
		<property name="preSalePermits">
			<column name="preSalePermits">
				<comment>预售证</comment>
			</column>
		</property>
	</class>
</hibernate-mapping>